{"Outdoor": {
    "id": "11",
    "name": "Наружные работы",
    "src": "/Outdoor.jpeg",
    "works": [{
        "id": 1,
        "title": "Подвес проводов на опорах"
    },
    {
        "id": 2,
        "title": "Устройство кабельных траншей"
    },
    {
        "id": 3,
        "title": "Бурение отверстий в грунте для установки опор"
    },
    {
        "id": 4,
        "title": "Установка опор и кронштейнов"
    },
    {
        "id": 5,
        "title": "Бетонные работы на линиях(бетонирование опор, фундаменты подстанций)"
    },
    {
        "id": 6,
        "title": "Устройство контура заземления"
    }]
},
"ElectricPanel": {
    "id": "12",
    "name": "Установка распределительных устройств",
    "src": "/Panel.jpg",
    "works": [{
        "id": 21,
        "title": "Установка шкафов и щитов внутри помещений"
    },
    {
        "id": 22,
        "title": "Установка шкафов и щитов открыто на бетонные основания"
    },
    {
        "id": 23,
        "title": "Установка и замена этажных щитов в МКД"
    },
    {
        "id": 24,
        "title": "Установка и замена квартирных щитов любой сложности"
    },
    {
        "id": 25,
        "title": "Установка и модернизация трансформаторных подстанций"
    }]
},
"Indoor": {
    "id": "13",
    "name": "Внутренние работы",
    "src": "/Panel.jpg",
    "works": [{
        "id": 31,
        "title": "Штробление стен под прокладку линий"
    },
    {
        "id": 32,
        "title": "Укладка кабелей по любой траектории"
    },
    {
        "id": 33,
        "title": "Установка и подключение любых конечных устройств от лампочки до станка"
    },
    {
        "id": 34,
        "title": "Модернизация сетей бытовых и производственных помещений"
    },
    {
        "id": 35,
        "title": "Установка лотков, труб для прокладки кабельной продукции"
    },
    {
        "id": 36,
        "title": "Прокладка слаботочных и оптических кабелей"
    }]
},
"Road": {
    "id": "14",
    "name": "Дорожное строительство",
    "src": "/Panel.jpg",
    "works": [{
        "id": 41,
        "title": "Установка и замена опор освещения"
    },
    {
        "id": 42,
        "title": "Установка светофорных обьектов"
    },
    {
        "id": 43,
        "title": "Установка опор для комплексов камер дорожного движения, в том числе с солнечными панелями"
    },
    {
        "id": 44,
        "title": "Бурение ям для любых дорожных знаков и указателей"
    },
    {
        "id": 45,
        "title": "Модернизация сетей, демонтаж бетонных опор"
    }]
}}